dnz/__init__.py
dnz/cli.py
dnz/engine.py
dnz/host.py
dnz/scanner.py
dnz/utils.py
dnz/engines/__init__.py
dnz/engines/dns_bruteforce_engine.py
dnz/engines/scanning_services.py
dnz/engines/simple_dns.py
dnz/engines/web_search.py
dnz/engines/word_list.py
dnz-0.1.0.dist-info/METADATA
dnz-0.1.0.dist-info/RECORD
dnz-0.1.0.dist-info/WHEEL
dnz-0.1.0.dist-info/entry_points.txt
dnz-0.1.0.dist-info/top_level.txt
